AsyncioLolzAPI.py
asynciololzapi-0.1.0.dist-info/WHEEL
asynciololzapi-0.1.0.dist-info/METADATA
asynciololzapi-0.1.0.dist-info/RECORD
