Metadata-Version: 2.1
Name: asynciololzapi
Version: 0.1.0
Summary: Асинхронная версия модуля LolzAPI
Author: Shemdy
Requires-Python: >=3.10,<3.11
Classifier: Programming Language :: Python :: 3
Classifier: Programming Language :: Python :: 3.10
